dioptra/client/__init__.py
dioptra/client/__version__.py
dioptra/client/_client.py
dioptra/generics_plugins/estimator_predict/__init__.py
dioptra/generics_plugins/estimator_predict/tf_keras_model.py
dioptra/generics_plugins/fit_estimator/__init__.py
dioptra/generics_plugins/fit_estimator/tf_keras_model.py
dioptra/pyplugs/__init__.py
dioptra/pyplugs/__version__.py
dioptra/pyplugs/_plugins.py
dioptra/restapi/__init__.py
dioptra/restapi/__version__.py
dioptra/restapi/app.py
dioptra/restapi/bootstrap.py
dioptra/restapi/config.py
dioptra/restapi/custom_schema_fields.py
dioptra/restapi/errors.py
dioptra/restapi/routes.py
dioptra/restapi/utils.py
dioptra/restapi/cli/__init__.py
dioptra/restapi/cli/gunicorn.py
dioptra/restapi/db/__init__.py
dioptra/restapi/db/custom_types.py
dioptra/restapi/db/db.py
dioptra/restapi/db/alembic/README
dioptra/restapi/db/alembic/alembic.ini
dioptra/restapi/db/alembic/env.py
dioptra/restapi/db/alembic/run.py
dioptra/restapi/db/alembic/script.py.mako
dioptra/restapi/db/alembic/versions/018130a0bf6c_.py
dioptra/restapi/db/alembic/versions/10f9e72e72aa_add_readonly_resource_lock_type_to_db_.py
dioptra/restapi/db/alembic/versions/148c032ffbd8_create_tables_for_v1_schema.py
dioptra/restapi/db/alembic/versions/32d5c0055e1b_.py
dioptra/restapi/db/alembic/versions/4b2d781f8bb4_remove_legacy_v0_tables.py
dioptra/restapi/db/alembic/versions/5b80d059cbb4_fix_primary_key_and_unique_index_on_.py
dioptra/restapi/db/alembic/versions/6a343ff9bc2f_.py
dioptra/restapi/db/alembic/versions/6a75ede23821_update_entry_point_parameter_types_list.py
dioptra/restapi/db/alembic/versions/7086ad09e884_.py
dioptra/restapi/db/alembic/versions/8ffe4640e009_update_uniqueness_constraint_name_for_.py
dioptra/restapi/db/alembic/versions/a278f46a1c9d_.py
dioptra/restapi/db/alembic/versions/b5cc97666e3d_add_index_over_the_draft_resources_payload.py
dioptra/restapi/db/alembic/versions/b835738272a8_insert_legacy_into_primary_key_constraint_names.py
dioptra_platform-1.0.1.dist-info/licenses/LICENSE
dioptra_platform-1.0.1.dist-info/METADATA
dioptra_platform-1.0.1.dist-info/WHEEL
dioptra_platform-1.0.1.dist-info/entry_points.txt
dioptra_platform-1.0.1.dist-info/top_level.txt
dioptra_platform-1.0.1.dist-info/RECORD
