Metadata-Version: 2.4
Name: dioptra-platform
Version: 1.0.1
Summary: Dioptra provides Machine Learning Security researchers with an environment for organizing and running experiments.
Author: Paul Scemama, Paul Rowe, Luke Barber, Cory Miniter
Author-email: James Glasbrenner <jglasbrenner@mitre.org>, Harold Booth <harold.booth@nist.gov>, Keith Manville <kmanville@mitre.org>, Julian Sexton <jtsexton@mitre.org>, Michael Andy Chisholm <chisholm@mitre.org>, Henry Choy <hchoy@mitre.org>, Andrew Hand <ahand@mitre.org>, Bronwyn Hodges <bhodges@mitre.org>, Dmitry Cousin <dmitry.cousin@nist.gov>, Eric Trapnell <eric.trapnell@nist.gov>, Mark Trapnell <mark.trapnell@nist.gov>, Howard Huang <hhuang@mitre.org>, Alexander Byrne <alexanderbyrne@mitr
Maintainer-email: James Glasbrenner <jglasbrenner@mitre.org>, Keith Manville <kmanville@mitre.org>, Harold Booth <harold.booth@nist.gov>
Project-URL: repository, https://github.com/usnistgov/dioptra
Project-URL: documentation, https://pages.nist.gov/dioptra
Project-URL: Changelog, https://github.com/usnistgov/dioptra/blob/main/CHANGELOG.md
Project-URL: Issue Tracker, https://github.com/usnistgov/dioptra/issues
Classifier: Development Status :: 5 - Production/Stable
Classifier: Framework :: Flask
Classifier: Intended Audience :: Science/Research
Classifier: Operating System :: OS Independent
Classifier: Programming Language :: Python :: 3 :: Only
Classifier: Programming Language :: Python :: 3.11
Classifier: Topic :: Scientific/Engineering :: Artificial Intelligence
Classifier: Topic :: Security
Requires-Python: >=3.11
License-File: LICENSE
Requires-Dist: alembic>=1.13.0
Requires-Dist: boto3>=1.16.0
Requires-Dist: Click<9,>=8.0.0
Requires-Dist: entrypoints>=0.3
Requires-Dist: Flask>=2.0.0
Requires-Dist: flask-accepts>=0.17.0
Requires-Dist: Flask-Cors>=3.0.1
Requires-Dist: Flask-Login>=0.6.0
Requires-Dist: Flask-Migrate>=2.5.0
Requires-Dist: flask-restx>=0.5.1
Requires-Dist: Flask-SQLAlchemy>=2.4.0
Requires-Dist: injector>=0.18.0
Requires-Dist: jsonschema>=4.17.0
Requires-Dist: marshmallow<4,>=3.9.0
Requires-Dist: multimethod>=1.5
Requires-Dist: numpy>=1.22.0
Requires-Dist: pandas>=1.5.0
Requires-Dist: passlib>=1.7.0
Requires-Dist: pyparsing>=3.1.0
Requires-Dist: python-dateutil>=2.8.0
Requires-Dist: PyYAML>=6.0.0
Requires-Dist: redis>=3.5.0
Requires-Dist: requests<3,>=2.25
Requires-Dist: rq>=1.5.0
Requires-Dist: scipy>=1.4.1
Requires-Dist: structlog>=20.2.0
Requires-Dist: SQLAlchemy>=2
Requires-Dist: typing-extensions>=3.7.4.3
Requires-Dist: werkzeug>=3.0.0
Provides-Extra: cookiecutter
Requires-Dist: cookiecutter<2.2.0,>=2.0.0; extra == "cookiecutter"
Provides-Extra: mlflow-skinny
Requires-Dist: mlflow-skinny>=2; extra == "mlflow-skinny"
Provides-Extra: mlflow-full
Requires-Dist: mlflow>=2; extra == "mlflow-full"
Provides-Extra: examples
Requires-Dist: aiohttp>=3.8.0; extra == "examples"
Requires-Dist: kaggle>=1.5.0; extra == "examples"
Requires-Dist: Pillow>=9.2.0; extra == "examples"
Requires-Dist: rich>=13.3.0; extra == "examples"
Requires-Dist: universal_pathlib>=0.0.23; extra == "examples"
Provides-Extra: postgres
Requires-Dist: psycopg2-binary>=2.9.0; extra == "postgres"
Provides-Extra: worker
Requires-Dist: async_timeout; extra == "worker"
Requires-Dist: adversarial-robustness-toolbox>=1.9.0; extra == "worker"
Requires-Dist: imgaug>=0.4.0; extra == "worker"
Requires-Dist: matplotlib; extra == "worker"
Requires-Dist: nrtk>=0.3.0; extra == "worker"
Requires-Dist: opencv-python; extra == "worker"
Requires-Dist: Pillow>=9.2.0; extra == "worker"
Requires-Dist: prefect<2,>=1.0.0; extra == "worker"
Requires-Dist: pyarrow; extra == "worker"
Requires-Dist: pycocotools; extra == "worker"
Requires-Dist: python-json-logger>=2.0.0; extra == "worker"
Requires-Dist: rich>=13.3.0; extra == "worker"
Requires-Dist: scikit-learn>=1.0.0; extra == "worker"
Requires-Dist: simplejson; extra == "worker"
Requires-Dist: tensorboard; extra == "worker"
Provides-Extra: dev
Requires-Dist: autopep8; extra == "dev"
Requires-Dist: binaryornot>=0.4.0; extra == "dev"
Requires-Dist: build; extra == "dev"
Requires-Dist: entrypoints; extra == "dev"
Requires-Dist: esbonio; extra == "dev"
Requires-Dist: Faker>=24.0.0; extra == "dev"
Requires-Dist: flake8-bugbear; extra == "dev"
Requires-Dist: flake8>=3.8.0; extra == "dev"
Requires-Dist: freezegun; extra == "dev"
Requires-Dist: ipykernel; extra == "dev"
Requires-Dist: ipython; extra == "dev"
Requires-Dist: jupyter; extra == "dev"
Requires-Dist: jupyterlab; extra == "dev"
Requires-Dist: nbconvert; extra == "dev"
Requires-Dist: pip-tools; extra == "dev"
Requires-Dist: pycodestyle; extra == "dev"
Requires-Dist: pydocstyle; extra == "dev"
Requires-Dist: pytest-cookies; extra == "dev"
Requires-Dist: pytest>=7; extra == "dev"
Requires-Dist: pytoml; extra == "dev"
Requires-Dist: Sphinx<5,>=4.5.0; extra == "dev"
Requires-Dist: tomli; extra == "dev"
Requires-Dist: tox>=4.4.0; extra == "dev"
Requires-Dist: wheel; extra == "dev"
Dynamic: license-file
